boundedfbm/__init__.py
boundedfbm/cells/__init__.py
boundedfbm/cells/base_cell.py
boundedfbm/cells/cell_factory.py
boundedfbm/cells/ovoid_cell.py
boundedfbm/cells/rectangular_cell.py
boundedfbm/cells/rod_cell.py
boundedfbm/cells/spherical_cell.py
boundedfbm/cells/typedefs.py
boundedfbm/motion/FBM.py
boundedfbm/motion/__init__.py
boundedfbm/probabilityfuncs/__init__.py
boundedfbm/probabilityfuncs/markov_chain.py
boundedfbm-0.4.0.dist-info/METADATA
boundedfbm-0.4.0.dist-info/WHEEL
boundedfbm-0.4.0.dist-info/RECORD
