Metadata-Version: 2.4
Name: boundedfbm
Version: 0.4.0
Summary: Generate bounded factional Brownian motion in up to 3 dimensions using Pyvista models for shapes.
Project-URL: Documentation, https://joemans3.github.io/boundedfbm/
Project-URL: Source code, https://github.com/joemans3/boundedfbm
Author-email: Baljyot Singh Parmar <baljyotparmar@hotmail.com>
Maintainer-email: Baljyot Singh Parmar <baljyotparmar@hotmail.com>
Requires-Python: >=3.12
Requires-Dist: numpy>=2.2.3
Requires-Dist: pyvista>=0.44.2
Requires-Dist: scipy>=1.15.2
Requires-Dist: typing-extensions>=4.12.2
